bidsprep/__init__.py
bidsprep/_decorators.py
bidsprep/_exceptions.py
bidsprep/_helpers.py
bidsprep/io.py
bidsprep/logger.py
bidsprep/simulate.py
bidsprep/utils.py
bidsprep-0.0.7.dist-info/licenses/LICENSE
bidsprep-0.0.7.dist-info/METADATA
bidsprep-0.0.7.dist-info/WHEEL
bidsprep-0.0.7.dist-info/top_level.txt
bidsprep-0.0.7.dist-info/RECORD
