Metadata-Version: 2.4
Name: bidsprep
Version: 0.0.7
Summary: Toolkit for making MRI data BIDS compatible.
Author-email: Donisha Smith <dsmit420@jhu.edu>
License-Expression: MIT
Project-URL: Homepage, https://bidsprep.readthedocs.io
Project-URL: Github, https://github.com/donishadsmith/bidsprep
Project-URL: Issues, https://github.com/donishadsmith/bidsprep/issues
Project-URL: Changelog, https://bidsprep.readthedocs.io/en/stable/changelog.html
Keywords: python,neuroimaging,fMRI,MRI,BIDS,NIfTI
Classifier: Intended Audience :: Education
Classifier: Intended Audience :: Science/Research
Classifier: Topic :: Scientific/Engineering
Classifier: Programming Language :: Python :: 3.10
Classifier: Programming Language :: Python :: 3.11
Classifier: Programming Language :: Python :: 3.12
Classifier: Programming Language :: Python :: 3.13
Classifier: Programming Language :: Python :: 3.14
Classifier: Operating System :: MacOS :: MacOS X
Classifier: Operating System :: POSIX :: Linux
Classifier: Operating System :: Microsoft :: Windows :: Windows 11
Classifier: Development Status :: 3 - Alpha
Requires-Python: >=3.10.0
License-File: LICENSE
Requires-Dist: numpy>=1.26.3
Requires-Dist: nibabel>=5.0.0
Requires-Dist: rich>=14.2.0
Requires-Dist: nilearn>=0.10.4
Requires-Dist: pandas>=2.1.0
Provides-Extra: all
Requires-Dist: bidsprep[test]; extra == "all"
Provides-Extra: test
Requires-Dist: pytest; extra == "test"
Requires-Dist: pytest-cov; extra == "test"
Dynamic: license-file
